noise_img_generator/__init__.py
noise_img_generator/__main__.py
noise_img_generator/generators.py
noise_img_generator/perlin.py
noise_img_generator/utils.py
noise_img_generator-1.0.7.dist-info/LICENSE
noise_img_generator-1.0.7.dist-info/METADATA
noise_img_generator-1.0.7.dist-info/WHEEL
noise_img_generator-1.0.7.dist-info/entry_points.txt
noise_img_generator-1.0.7.dist-info/top_level.txt
noise_img_generator-1.0.7.dist-info/RECORD
