Metadata-Version: 2.1
Name: noise-img-generator
Version: 1.0.7
Summary: CLI to generate noise images for use in game design
Home-page: https://github.com/slaterb1/noise-img-generator
Author: Benjamin Slater
Author-email: benjamin.ed.slater@gmail.com
License: UNKNOWN
Project-URL: Bug Tracker, https://github.com/slaterb1/noise_img_generator/issues
Project-URL: Source, https://github.com/slaterb1/noise_img_generator
Platform: UNKNOWN
Classifier: Programming Language :: Python :: 3
Classifier: Operating System :: OS Independent
Requires-Python: >=3.6
Requires-Dist: numpy
Requires-Dist: pypng
